{
  "model": "general.GenModelo",
  "data": [
    {"id": 10001, "app": "general",      "clase": "GenContacto",        "nombre": "Contacto",         "tabla": "gen_contacto",         "tipo": "A"},
    {"id": 10002, "app": "general",      "clase": "GenDocumento",       "nombre": "Documento",        "tabla": "gen_documento",        "tipo": "M"},
    {"id": 10003, "app": "general",      "clase": "GenResponsabilidad", "nombre": "Responsabilidad",  "tabla": "gen_responsabilidad",  "tipo": "F"},
    {"id": 10004, "app": "general",      "clase": "GenItem",            "nombre": "Item",             "tabla": "gen_item",             "tipo": "A"},
    {"id": 10005, "app": "general",      "clase": "GenDocumentoDetalle","nombre": "Documento detalle","tabla": "gen_documento_detalle","tipo": "D"},

    {"id": 20001, "app": "contabilidad", "clase": "ConComprobante",     "nombre": "Comprobante",      "tabla": "con_comprobante",      "tipo": "F"},
    {"id": 20002, "app": "contabilidad", "clase": "ConCuenta",          "nombre": "Cuenta",           "tabla": "con_cuenta",           "tipo": "A"},
    {"id": 20003, "app": "contabilidad", "clase": "ConCuentaClase",     "nombre": "Cuenta clase",     "tabla": "con_cuenta_clase",     "tipo": "F"},
    {"id": 20004, "app": "contabilidad", "clase": "ConCuentaGrupo",     "nombre": "Cuenta grupo",     "tabla": "con_cuenta_grupo",     "tipo": "F"},
    {"id": 20005, "app": "contabilidad", "clase": "ConCuentaCuenta",    "nombre": "Cuenta cuenta",    "tabla": "con_cuenta_cuenta",    "tipo": "F"},
    {"id": 20006, "app": "contabilidad", "clase": "ConCuentaSubcuenta", "nombre": "Cuenta subcuenta", "tabla": "con_cuenta_subcuenta", "tipo": "F"},
    {"id": 20007, "app": "contabilidad", "clase": "ConCentroCosto",      "nombre": "Centro de costo",  "tabla": "con_centro_costo",     "tipo": "A"},

    {"id": 30001, "app": "turno",        "clase": "TurProgramador",     "nombre": "Programador",      "tabla": "tur_programador",      "tipo": "A"},
    {"id": 30002, "app": "turno",        "clase": "TurPuesto",          "nombre": "Puesto",           "tabla": "tur_puesto",           "tipo": "A"}
  ]
}
